{
  "m_Version": 12,
  "DisplayName": "Ford Bronco Civilian",
  "Icon": "Car",
  "Color": "C90076",
  "IsExchange": 0,
  "InitStockPercent": 75,
  "Items": [
    {
      "ClassName": "FordBronco",
      "MaxPriceThreshold": 450000,
      "MinPriceThreshold": 450000,
      "SellPricePercent": -1,
      "MaxStockThreshold": 1,
      "MinStockThreshold": 1,
      "QuantityPercent": -1,
      "SpawnAttachments": [
        "carbattery",
        "carradiator",
        "sparkplug",
        "headlighth7",
        "headlighth7",
        "FordBronco_Driver",
        "FordBronco_CoDriver",
        "FordBronco_Hood",
        "FordBronco_Trunk",
        "FordBronco_Wheel",
        "FordBronco_Wheel",
        "FordBronco_Wheel",
        "FordBronco_Wheel",
        "FordBronco_Wheel"
      ],
      "Variants": []
    },
    {
      "ClassName": "FordBroncoRust",
      "MaxPriceThreshold": 450000,
      "MinPriceThreshold": 450000,
      "SellPricePercent": -1,
      "MaxStockThreshold": 1,
      "MinStockThreshold": 1,
      "QuantityPercent": -1,
      "SpawnAttachments": [
        "carbattery",
        "carradiator",
        "sparkplug",
        "headlighth7",
        "headlighth7",
        "FordBronco_DriverRust",
        "FordBronco_CoDriverRust",
        "FordBronco_TrunkRust",
        "FordBronco_HoodRust",
        "FordBronco_Wheel",
        "FordBronco_Wheel",
        "FordBronco_Wheel",
        "FordBronco_Wheel",
        "FordBronco_Wheel"
      ],
      "Variants": []
    },
    {
      "ClassName": "FordBroncoCIV",
      "MaxPriceThreshold": 450000,
      "MinPriceThreshold": 450000,
      "SellPricePercent": -1,
      "MaxStockThreshold": 1,
      "MinStockThreshold": 1,
      "QuantityPercent": -1,
      "SpawnAttachments": [
        "carbattery",
        "carradiator",
        "sparkplug",
        "headlighth7",
        "headlighth7",
        "FordBronco_Driver",
        "FordBronco_CoDriver",
        "FordBronco_Trunk",
        "FordBronco_Hood",
        "FordBronco_Wheel",
        "FordBronco_Wheel",
        "FordBronco_Wheel",
        "FordBronco_Wheel",
        "FordBronco_Wheel"
      ],
      "Variants": []
    },
    {
      "ClassName": "FordBroncoCIVRust",
      "MaxPriceThreshold": 450000,
      "MinPriceThreshold": 450000,
      "SellPricePercent": -1,
      "MaxStockThreshold": 1,
      "MinStockThreshold": 1,
      "QuantityPercent": -1,
      "SpawnAttachments": [
        "carbattery",
        "carradiator",
        "sparkplug",
        "headlighth7",
        "headlighth7",
        "FordBronco_DriverRust",
        "FordBronco_CoDriverRust",
        "FordBronco_TrunkRust",
        "FordBronco_HoodRust",
        "FordBronco_Wheel",
        "FordBronco_Wheel",
        "FordBronco_Wheel",
        "FordBronco_Wheel",
        "FordBronco_Wheel"
      ],
      "Variants": []
    }
  ]
}